LICENSE.txt
MANIFEST.in
README.md
setup.cfg
setup.py
optconvert/__init__.py
optconvert/command_line.py
optconvert/const.py
optconvert/converter.py
optconvert/model.py
optconvert/mpl_with_ext_data.py
optconvert.egg-info/PKG-INFO
optconvert.egg-info/SOURCES.txt
optconvert.egg-info/dependency_links.txt
optconvert.egg-info/entry_points.txt
optconvert.egg-info/requires.txt
optconvert.egg-info/top_level.txt
tests/Dakota_det.lp
tests/Dakota_det.mpl
tests/Dakota_det.mps
tests/Dakota_det.trk
tests/Dakota_det_converted.sim
tests/Dakota_det_wrong.mpl
tests/SNDP_TestCase_14.cor
tests/SNDP_TestCase_14.mpl
tests/SNDP_TestCase_14.sto
tests/SNDP_TestCase_14.tim
tests/SNDP_default.mpl
tests/SNDP_default_ArcProduct.dat
tests/SNDP_default_Demand.dat
tests/SNDP_default_MaterialReq.dat
tests/SNDP_default_Prob.dat
tests/SNDP_default_ScalarData.dat
tests/SNDP_default_ShipCost.dat
tests/SNDP_default_arc.dat
tests/SNDP_stochastic_MIP.mpl
tests/SNDP_stochastic_MIP.mps
tests/__init__.py
tests/cap_test_5.mpl
tests/cap_test_5_DATA.dat
tests/cap_test_5_RANDOM.dat
tests/cap_test_5_SETS.dat
tests/unit_tests.py