Metadata-Version: 2.1
Name: optconvert
Version: 0.0.1
Summary: Converter for mathematical optimization formats: .mpl, .lp, .xa, .sim, .mpl, .gms, .mod, .xml, .mat.
Home-page: https://github.com/pashtetgp/optconvert
Author: Pavlo Glushko
Author-email: pavloglushko@gmail.com
License: MIT
Download-URL: https://github.com/pashtetGP/optconvert/archive/0.0.1.tar.gz
Keywords: converter mathematical optimization mps
Platform: UNKNOWN
Classifier: Environment :: Console
Classifier: Intended Audience :: Science/Research
Classifier: Natural Language :: English
Classifier: Operating System :: Microsoft :: Windows
Classifier: Programming Language :: Python
Classifier: Programming Language :: Python :: 3.6
Classifier: Programming Language :: Python :: 3.7
Classifier: Programming Language :: Python :: 3.8
Classifier: Programming Language :: Python :: 3.9
Classifier: Topic :: Scientific/Engineering :: Mathematics
Requires-Python: >=3.6
